<cumulative_2009-04-30>
  <number_of_nodes value="201"/>
  <number_of_edges value="659"/>
  <directed value="0"/>
  <reciprocity value="1.0"/>
  <proportion_of_edges value="0.0327860696517"/>
  <size_main_strongly_connected_component value="148"/>
  <proportion_main_strongly_connected_component value="0.73631840796"/>
  <circuit_rank value="465"/>
  <number_of_communities value="31"/>
  <equivalent_number_of_communities value="21.7092960774"/>
  <modularity_Louvain_partition value="0.893809777592"/>
  <average_size_1_neighborhood value="7.55721393035"/>
  <std_size_1_neighborhood value="4.30872771551"/>
  <exponent_size_1_neighborhood value="1.91043979139"/>
  <average_size_2_neighborhood value="24.3333333333"/>
  <std_size_2_neighborhood value="13.0476864892"/>
  <exponent_size_2_neighborhood value="1.74380036148"/>
  <average_size_3_neighborhood value="44.5721393035"/>
  <std_size_3_neighborhood value="21.3260875421"/>
  <exponent_size_3_neighborhood value="2.28697434008"/>
  <average_proportion_1_neighborhood value="0.0375980792555"/>
  <std_proportion_1_neighborhood value="0.0214364562961"/>
  <exponent_proportion_1_neighborhood value="4.20871925152"/>
  <average_proportion_2_neighborhood value="0.121061359867"/>
  <std_proportion_2_neighborhood value="0.0649138631302"/>
  <exponent_proportion_2_neighborhood value="10.9789913715"/>
  <average_proportion_3_neighborhood value="0.221751936833"/>
  <std_proportion_3_neighborhood value="0.10609993802"/>
  <exponent_proportion_3_neighborhood value="55.3004596347"/>
  <average_degree value="6.55721393035"/>
  <std_degree value="4.30872771551"/>
  <exponent_degree value="2.01575708417"/>
  <max_degree value="21"/>
  <average_indegree value="6.55721393035"/>
  <std_indegree value="4.30872771551"/>
  <exponent_indegree value="2.01575708417"/>
  <max_indegree value="21"/>
  <average_outdegree value="6.55721393035"/>
  <std_outdegree value="4.30872771551"/>
  <exponent_outdegree value="2.01575708417"/>
  <max_outdegree value="21"/>
  <average_distance value="4.93517165814"/>
  <std_distance value="2.53683549337"/>
  <exponent_distance value="2.40900734391"/>
  <max_distance value="14"/>
  <balaban_index value="42.7352126639"/>
  <harary_index value="3068.55120435"/>
  <wiener_index value="54050"/>
  <efficiency value="0.282087810659"/>
  <average_radiality value="9.03125574554"/>
  <std_radiality value="0.915352530673"/>
  <exponent_radiality value="22.9279039178"/>
  <average_core_number value="4.19900497512"/>
  <std_core_number value="2.2571498351"/>
  <exponent_core_number value="0"/>
  <size_main_core value="11"/>
  <proportion_main_core value="0.0547263681592"/>
  <average_clustering value="0.467143841907"/>
  <std_clustering value="0.304225616976"/>
  <exponent_clustering value="3.11484558541"/>
  <average_neighbor_degree value="8.13188205283"/>
  <std_neighbor_degree value="3.28548020565"/>
  <exponent_neighbor_degree value="7.11624049308"/>
  <average_hubs value="0.00497512437811"/>
  <std_hubs value="0.0439706790351"/>
  <exponent_hubs value="1.25248494679"/>
  <average_authorities value="0.00497512437811"/>
  <std_authorities value="0.0439706790351"/>
  <exponent_authorities value="1.25248494679"/>
  <average_eigenvector_centrality value="0.00793013248243"/>
  <std_eigenvector_centrality value="0.0700873553283"/>
  <exponent_eigenvector_centrality value="1.25248494679"/>
  <centralization_eigenvector value="1.06744840033"/>
  <average_pagerank value="0.00497512437811"/>
  <std_pagerank value="0.00266473631145"/>
  <exponent_pagerank value="5.90979592709"/>
  <average_closeness_centrality value="0.126751776692"/>
  <std_closeness_centrality value="0.0496500269264"/>
  <exponent_closeness_centrality value="11.0565485227"/>
  <centralization_closeness value="0.156929907343"/>
  <average_betweenness_centrality value="0.0111237780945"/>
  <std_betweenness_centrality value="0.023104328338"/>
  <exponent_betweenness_centrality value="1.80210186631"/>
  <centralization_betweenness value="0.125121424488"/>
  <average_load_centrality value="0.0111237780945"/>
  <std_load_centrality value="0.0227497286355"/>
  <exponent_load_centrality value="1.79923031773"/>
  <centralization_load value="0.117044200879"/>
  <transitivity value="0.459117221418"/>
  <size_center value="3"/>
  <proportion_center value="0.0149253731343"/>
  <size_periphery value="4"/>
  <proportion_periphery value="0.0199004975124"/>
  <average_eccentricity value="10.3851351351"/>
  <std_eccentricity value="1.36818902128"/>
  <exponent_eccentricity value="0"/>
  <radius value="7"/>
  <diameter value="14"/>
  <maximum_laplacian_eigenvalue value="729.284244593"/>
  <average_laplacian_eigenvalue value="62.776119403"/>
  <std_laplacian_eigenvalue value="92.7645316659"/>
  <algebraic_connectivity value="-1.51843211137e-15"/>
  <minimum_adjacency_eigenvalue value="-345.129991832"/>
  <maximum_adjacency_eigenvalue value="346.482924303"/>
  <average_adjacency_eigenvalue value="-1.54399613329e-14"/>
  <std_adjacency_eigenvalue value="66.698176633"/>
  <size_dominating_set value="196"/>
  <proportion_dominating_set value="0.975124378109"/>
  <size_maximal_matching value="108"/>
  <proportion_maximal_matching value="0.163884673748"/>
  <size_vertex_cover value="172"/>
  <proportion_vertex_cover value="0.855721393035"/>
  <assortativity value="0.334392983465"/>
  <average_betweenness value="0.00423753765316"/>
  <std_betweenness value="0.00982346147311"/>
  <exponent_betweenness value="2.19690474681"/>
  <average_edgeload value="464.84370258"/>
  <std_edgeload value="716.37695442"/>
  <exponent_edgeload value="2.64469191862"/>
</cumulative_2009-04-30>
