<cumulative_2009-07-14>
  <number_of_nodes value="288"/>
  <number_of_edges value="1761"/>
  <directed value="0"/>
  <reciprocity value="1.0"/>
  <proportion_of_edges value="0.0426103368177"/>
  <size_main_strongly_connected_component value="282"/>
  <proportion_main_strongly_connected_component value="0.979166666667"/>
  <circuit_rank value="1477"/>
  <number_of_communities value="23"/>
  <equivalent_number_of_communities value="14.26625387"/>
  <modularity_Louvain_partition value="0.805480742943"/>
  <average_size_1_neighborhood value="13.2291666667"/>
  <std_size_1_neighborhood value="9.23588919951"/>
  <exponent_size_1_neighborhood value="2.1021791243"/>
  <average_size_2_neighborhood value="77.5555555556"/>
  <std_size_2_neighborhood value="46.8318175582"/>
  <exponent_size_2_neighborhood value="1.91996458435"/>
  <average_size_3_neighborhood value="151.430555556"/>
  <std_size_3_neighborhood value="66.5408868435"/>
  <exponent_size_3_neighborhood value="1.48676629773"/>
  <average_proportion_1_neighborhood value="0.0459346064815"/>
  <std_proportion_1_neighborhood value="0.0320690597205"/>
  <exponent_proportion_1_neighborhood value="4.92551739131"/>
  <average_proportion_2_neighborhood value="0.269290123457"/>
  <std_proportion_2_neighborhood value="0.162610477633"/>
  <exponent_proportion_2_neighborhood value="14.5567011077"/>
  <average_proportion_3_neighborhood value="0.525800540123"/>
  <std_proportion_3_neighborhood value="0.231044745984"/>
  <exponent_proportion_3_neighborhood value="99.2346491026"/>
  <average_degree value="12.2291666667"/>
  <std_degree value="9.23588919951"/>
  <exponent_degree value="2.14061896169"/>
  <max_degree value="51"/>
  <average_indegree value="12.2291666667"/>
  <std_indegree value="9.23588919951"/>
  <exponent_indegree value="2.14061896169"/>
  <max_indegree value="51"/>
  <average_outdegree value="12.2291666667"/>
  <std_outdegree value="9.23588919951"/>
  <exponent_outdegree value="2.14061896169"/>
  <max_outdegree value="51"/>
  <average_distance value="3.77636939792"/>
  <std_distance value="1.80996657211"/>
  <exponent_distance value="3.34199486878"/>
  <max_distance value="10"/>
  <balaban_index value="91.9934578365"/>
  <harary_index value="13403.7015873"/>
  <wiener_index value="150156"/>
  <efficiency value="0.338297912403"/>
  <average_radiality value="6.21019156508"/>
  <std_radiality value="0.879328104072"/>
  <exponent_radiality value="56.7370628863"/>
  <average_core_number value="7.28819444444"/>
  <std_core_number value="3.43646694634"/>
  <exponent_core_number value="1.8763100056"/>
  <size_main_core value="16"/>
  <proportion_main_core value="0.0555555555556"/>
  <average_clustering value="0.392851985816"/>
  <std_clustering value="0.231171529943"/>
  <exponent_clustering value="3.71288045233"/>
  <average_neighbor_degree value="16.52099638"/>
  <std_neighbor_degree value="6.8108319949"/>
  <exponent_neighbor_degree value="10.5570289176"/>
  <average_hubs value="0.00347222222222"/>
  <std_hubs value="0.0271808804652"/>
  <exponent_hubs value="1.56235420573"/>
  <average_authorities value="0.00347222222222"/>
  <std_authorities value="0.0271808804652"/>
  <exponent_authorities value="1.56235420573"/>
  <average_eigenvector_centrality value="0.00746676993248"/>
  <std_eigenvector_centrality value="0.0584505737268"/>
  <exponent_eigenvector_centrality value="1.56235420573"/>
  <centralization_eigenvector value="0.795595167601"/>
  <average_pagerank value="0.00347222222222"/>
  <std_pagerank value="0.00193964340507"/>
  <exponent_pagerank value="5.23242732112"/>
  <average_closeness_centrality value="0.264757114887"/>
  <std_closeness_centrality value="0.0641233560282"/>
  <exponent_closeness_centrality value="23.7396682561"/>
  <centralization_closeness value="0.208184983033"/>
  <average_betweenness_centrality value="0.00935167474802"/>
  <std_betweenness_centrality value="0.0256879663333"/>
  <exponent_betweenness_centrality value="2.00726768017"/>
  <centralization_betweenness value="0.245679689403"/>
  <average_load_centrality value="0.00935167474802"/>
  <std_load_centrality value="0.0252916576448"/>
  <exponent_load_centrality value="2.0025118691"/>
  <centralization_load value="0.242047851329"/>
  <transitivity value="0.309189593861"/>
  <size_center value="3"/>
  <proportion_center value="0.0104166666667"/>
  <size_periphery value="5"/>
  <proportion_periphery value="0.0173611111111"/>
  <average_eccentricity value="7.6914893617"/>
  <std_eccentricity value="0.97515151481"/>
  <exponent_eccentricity value="82.3680003061"/>
  <radius value="5"/>
  <diameter value="10"/>
  <maximum_laplacian_eigenvalue value="524.083369647"/>
  <average_laplacian_eigenvalue value="90.1041666667"/>
  <std_laplacian_eigenvalue value="106.516151537"/>
  <algebraic_connectivity value="-2.26694804042e-14"/>
  <minimum_adjacency_eigenvalue value="-187.268021714"/>
  <maximum_adjacency_eigenvalue value="311.569317014"/>
  <average_adjacency_eigenvalue value="8.50932461068e-15"/>
  <std_adjacency_eigenvalue value="63.8899335663"/>
  <size_dominating_set value="269"/>
  <proportion_dominating_set value="0.934027777778"/>
  <size_maximal_matching value="178"/>
  <proportion_maximal_matching value="0.101078932425"/>
  <size_vertex_cover value="266"/>
  <proportion_vertex_cover value="0.923611111111"/>
  <assortativity value="0.222564741348"/>
  <average_betweenness value="0.00206327111945"/>
  <std_betweenness value="0.00756629346831"/>
  <exponent_betweenness value="2.42523359467"/>
  <average_edgeload value="672.741056218"/>
  <std_edgeload value="1636.91337117"/>
  <exponent_edgeload value="2.92131203615"/>
</cumulative_2009-07-14>
