<Freemans>
  <number_of_nodes value="34"/>
  <number_of_vertices value="474"/>
  <proportion_of_vertices value="0.844919786096"/>
  <number_of_communities value="2"/>
  <number_of_equivalent_communities value="1.97269624573"/>
  <average_degree value="27.8823529412"/>
  <std_degree value="4.56176375773"/>
  <average_distance value="1.12110726644"/>
  <std_distance value="0.406526537712"/>
  <average_clustering value="0.888223254734"/>
  <std_clustering value="0.0317301878917"/>
  <average_importance value="0.167239666745"/>
  <std_importance value="0.0379823455421"/>
  <centralization_importance value="0.149511244133"/>
  <average_pagerank value="0.0294117647059"/>
  <std_pagerank value="0.00629582321124"/>
  <average_neighbor_degree value="28.6985640453"/>
  <std_neighbor_degree value="0.576459168846"/>
  <average_closeness_centrality value="0.876768417936"/>
  <std_closeness_centrality value="0.09308696752"/>
  <centralization_closeness value="0.257899428373"/>
  <average_betweeness_centrality value="0.00484625668449"/>
  <std_betweeness_centrality value="0.00273965856344"/>
  <centralization_betweenness value="0.00541268240913"/>
  <transitivity value="0.882177764203"/>
  <size_of_center value="3"/>
  <proportion_of_center value="0.0882352941176"/>
  <size_of_periphery value="31"/>
  <proportion_of_periphery value="0.911764705882"/>
  <average_eccentricity_of_network value="1.91176470588"/>
  <std_eccentricity_of_network value="0.283636787088"/>
  <radius_of_network value="1"/>
  <diameter_of_network value="2"/>
  <min_laplacian_eigenvalue value="1.42108547152e-14"/>
  <max_laplacian_eigenvalue value="99.3063448527"/>
  <mean_laplacian_eigenvalue value="59.5882352941"/>
  <std_laplacian_eigenvalue value="19.0542841362"/>
  <min_adjacency_eigenvalue value="-10.673862084"/>
  <max_adjacency_eigenvalue value="62.9374966704"/>
  <mean_adjacency_eigenvalue value="-2.73637321952e-15"/>
  <std_adjacency_eigenvalue value="11.9975487693"/>
  <minimum_size_spanning_tree value="33"/>
  <max_number_independant_nodes value="2"/>
  <max_proportion_independant_nodes value="0.0588235294118"/>
  <assortativity value="-0.112421123967"/>
  <average_edge_betweenness value="0.0024368780884"/>
  <std_edge_betweenness value="0.000533064128596"/>
  <average_communicability value="74023008856.4"/>
  <std_communicability value="16105069101.4"/>
</Freemans>
