<cumulative_2009-05-02>
  <number_of_nodes value="217"/>
  <number_of_edges value="967"/>
  <directed value="0"/>
  <reciprocity value="1.0"/>
  <proportion_of_edges value="0.0412613073903"/>
  <size_main_strongly_connected_component value="213"/>
  <proportion_main_strongly_connected_component value="0.981566820276"/>
  <circuit_rank value="754"/>
  <number_of_communities value="30"/>
  <equivalent_number_of_communities value="21.5905547914"/>
  <modularity_Louvain_partition value="0.866125023328"/>
  <average_size_1_neighborhood value="9.91244239631"/>
  <std_size_1_neighborhood value="5.56127840851"/>
  <exponent_size_1_neighborhood value="2.51056426794"/>
  <average_size_2_neighborhood value="40.1797235023"/>
  <std_size_2_neighborhood value="19.742348548"/>
  <exponent_size_2_neighborhood value="1.92438286258"/>
  <average_size_3_neighborhood value="65.2580645161"/>
  <std_size_3_neighborhood value="21.331004283"/>
  <exponent_size_3_neighborhood value="3.71051795561"/>
  <average_proportion_1_neighborhood value="0.0456794580475"/>
  <std_proportion_1_neighborhood value="0.0256280110991"/>
  <exponent_proportion_1_neighborhood value="6.09980060918"/>
  <average_proportion_2_neighborhood value="0.18516001614"/>
  <std_proportion_2_neighborhood value="0.0909785647373"/>
  <exponent_proportion_2_neighborhood value="6.11604600574"/>
  <average_proportion_3_neighborhood value="0.300728407908"/>
  <std_proportion_3_neighborhood value="0.0982995589076"/>
  <exponent_proportion_3_neighborhood value="12.1193154936"/>
  <average_degree value="8.91244239631"/>
  <std_degree value="5.56127840851"/>
  <exponent_degree value="2.17145508735"/>
  <max_degree value="37"/>
  <average_indegree value="8.91244239631"/>
  <std_indegree value="5.56127840851"/>
  <exponent_indegree value="2.17145508735"/>
  <max_indegree value="37"/>
  <average_outdegree value="8.91244239631"/>
  <std_outdegree value="5.56127840851"/>
  <exponent_outdegree value="2.17145508735"/>
  <max_outdegree value="37"/>
  <average_distance value="5.4367519672"/>
  <std_distance value="2.8337320348"/>
  <exponent_distance value="2.24607797667"/>
  <max_distance value="13"/>
  <balaban_index value="51.1745105824"/>
  <harary_index value="6004.83105783"/>
  <wiener_index value="123330"/>
  <efficiency value="0.265959387804"/>
  <average_radiality value="7.53760297635"/>
  <std_radiality value="0.928423673778"/>
  <exponent_radiality value="118.413517708"/>
  <average_core_number value="5.36405529954"/>
  <std_core_number value="2.16405451448"/>
  <exponent_core_number value="3.6017236877"/>
  <size_main_core value="27"/>
  <proportion_main_core value="0.124423963134"/>
  <average_clustering value="0.404555192954"/>
  <std_clustering value="0.223245109275"/>
  <exponent_clustering value="4.07595666434"/>
  <average_neighbor_degree value="10.8964225655"/>
  <std_neighbor_degree value="4.29169788058"/>
  <exponent_neighbor_degree value="20.5746171463"/>
  <average_hubs value="0.00460829493088"/>
  <std_hubs value="0.0294328927971"/>
  <exponent_hubs value="1.55172687135"/>
  <average_authorities value="0.00460829493088"/>
  <std_authorities value="0.0294328927971"/>
  <exponent_authorities value="1.55172687135"/>
  <average_eigenvector_centrality value="0.0105007059338"/>
  <std_eigenvector_centrality value="0.0670673549931"/>
  <exponent_eigenvector_centrality value="1.55172687135"/>
  <centralization_eigenvector value="0.801461697039"/>
  <average_pagerank value="0.00460829493088"/>
  <std_pagerank value="0.00166294544596"/>
  <exponent_pagerank value="7.05948221326"/>
  <average_closeness_centrality value="0.181304861419"/>
  <std_closeness_centrality value="0.0385472443754"/>
  <exponent_closeness_centrality value="11.0351611934"/>
  <centralization_closeness value="0.146521277368"/>
  <average_betweenness_centrality value="0.0199954750592"/>
  <std_betweenness_centrality value="0.0559086234759"/>
  <exponent_betweenness_centrality value="1.96050145574"/>
  <centralization_betweenness value="0.42832217454"/>
  <average_load_centrality value="0.0199954750592"/>
  <std_load_centrality value="0.055556662714"/>
  <exponent_load_centrality value="1.95065457935"/>
  <centralization_load value="0.428381276255"/>
  <transitivity value="0.334423548651"/>
  <size_center value="12"/>
  <proportion_center value="0.0552995391705"/>
  <size_periphery value="13"/>
  <proportion_periphery value="0.0599078341014"/>
  <average_eccentricity value="10.1877934272"/>
  <std_eccentricity value="1.79264048815"/>
  <exponent_eccentricity value="0"/>
  <radius value="7"/>
  <diameter value="13"/>
  <maximum_laplacian_eigenvalue value="312.131938239"/>
  <average_laplacian_eigenvalue value="70.3594470046"/>
  <std_laplacian_eigenvalue value="71.8334595649"/>
  <algebraic_connectivity value="-1.59045871963e-14"/>
  <minimum_adjacency_eigenvalue value="-143.77229863"/>
  <maximum_adjacency_eigenvalue value="169.76247451"/>
  <average_adjacency_eigenvalue value="-1.43009004536e-14"/>
  <std_adjacency_eigenvalue value="55.3069357573"/>
  <size_dominating_set value="210"/>
  <proportion_dominating_set value="0.967741935484"/>
  <size_maximal_matching value="130"/>
  <proportion_maximal_matching value="0.134436401241"/>
  <size_vertex_cover value="200"/>
  <proportion_vertex_cover value="0.921658986175"/>
  <assortativity value="0.263597861721"/>
  <average_betweenness value="0.00544204701559"/>
  <std_betweenness value="0.0217113642758"/>
  <exponent_betweenness value="2.03588860914"/>
  <average_edgeload value="720.566701138"/>
  <std_edgeload value="2414.01705493"/>
  <exponent_edgeload value="2.18727230154"/>
</cumulative_2009-05-02>
